[
  {
    "chainId": 9001,
    "address": "0xD4949664cD82660AaE99bEdc034a0deA8A0bd517",
    "name": "Wrapped Evmos",
    "symbol": "WEVMOS",
    "decimals": 18,
    "logoURI": "evmos/wevmos.png",
    "coinGeckoId": "evmos"
  },
  {
    "chainId": 9001,
    "address": "0x75aeE82a16BD1fB98b11879af93AB7CE055f66Da",
    "name": "xDiffusion",
    "symbol": "xDIFF",
    "decimals": 18,
    "logoURI": "evmos/xdiff.png"
  },
  {
    "chainId": 9001,
    "address": "0x3f75ceabCDfed1aCa03257Dc6Bdc0408E2b4b026",
    "name": "Diffusion",
    "symbol": "DIFF",
    "decimals": 18,
    "logoURI": "evmos/diff.png",
    "coinGeckoId": "diffusion"
  },
  {
    "chainId": 9001,
    "address": "0x47685B6AC7bB4de761A57828877A7B8254c8B145",
    "name": "Evmos Domains",
    "symbol": "EVD",
    "decimals": 18,
    "logoURI": "evmos/evd.png",
    "coinGeckoId": "evmos-domains"
  },
  {
    "chainId": 9001,
    "address": "0x181C262b973B22C307C646a67f64B76410D19b6B",
    "name": "EvmoSwap Token",
    "symbol": "EMO",
    "decimals": 18,
    "logoURI": "evmos/emo.png",
    "coinGeckoId": "evmoswap"
  },
  {
    "chainId": 9001,
    "address": "0xBbD37BF85f7474b5bDe689695674faB1888565Ad",
    "name": "OAV",
    "symbol": "OAV",
    "decimals": 18,
    "logoURI": "evmos/oav.png",
    "coinGeckoId": ""
  },
  {
    "chainId": 9001,
    "address": "0xe46910336479F254723710D57e7b683F3315b22B",
    "name": "USD Coin (Celer)",
    "symbol": "ceUSDC",
    "decimals": 6,
    "logoURI": "ethereum/usdc.png",
    "coinGeckoId": ""
  },
  {
    "chainId": 9001,
    "address": "0xb72A7567847abA28A2819B855D7fE679D4f59846",
    "name": "Tether USD (Celer)",
    "symbol": "ceUSDT",
    "decimals": 6,
    "logoURI": "ethereum/usdt.png",
    "coinGeckoId": ""
  },
  {
    "chainId": 9001,
    "address": "0x940dAAbA3F713abFabD79CdD991466fe698CBe54",
    "name": "Dai Stablecoin (Celer)",
    "symbol": "ceDAI",
    "decimals": 18,
    "logoURI": "ethereum/dai.png",
    "coinGeckoId": ""
  }
]
